{"fmfwio": 1, "exmo": 1, "bw": 1, "okex": 1, "binance": 1, "okex5": 1, "aax": 1, "bigone": 1, "ftx": 1, "therock": 1, "currencycom": 1, "bitcoincom": 1, "bitget": 1, "huobi": 1, "coinex": 1, "bitstamp": 1, "zb": 1, "gateio": 1, "bittrex": 1, "ascendex": 1, "coinbaseprime": 1, "lbank": 1, "cryptocom": 1, "timex": 1, "gate": 1, "btcturk": 1, "bequant": 1, "wavesexchange": 1, "mexc3": 1, "bitmart": 1, "tidebit": 1, "ftxus": 1, "probit": 1, "whitebit": 1, "bytetrade": 1, "crex24": 1, "kucoin": 1, "kraken": 1, "okx": 1, "binanceusdm": 1, "bitbay": 1, "coinbasepro": 1, "hollaex": 1, "bitso": 1, "bitforex": 1, "binanceus": 1, "lbank2": 1, "zonda": 1, "novadax": 1, "bitfinex": 1, "hitbtc": 1, "huobipro": 1, "bibox": 1, "phemex": 1, "hitbtc3": 1, "bitfinex2": 1, "mexc": 1, "ndax": 1}